{"platform":"ASOMATE-ESP","data":[{"name":"av-scene","odatype":"avanzadas","active":true,"minimize":false,"binds":{},"attr":{"class":"","v-bind:automatic-scene":true},"content":[{"name":"av-start","odatype":"avanzadas","active":true,"minimize":false,"binds":{},"attr":{},"content":[],"id":"ComenzarODA","location":"0,0"}],"id":"Comenzar","location":"0"},{"name":"av-scene","odatype":"avanzadas","active":true,"minimize":false,"binds":{},"attr":{"class":"","v-bind:automatic-scene":true},"content":[{"name":"av-info","odatype":"avanzadas","active":true,"minimize":false,"binds":{},"attr":{"title":"¿Dónde hay seis?","interaction":"select","class":""},"content":[{"name":"module-audiotext","active":true,"minimize":false,"odatype":"avanzadas","binds":{},"attr":{"text":"Presta atención al número que aparece del lado izquierdo. Después selecciona el recuadro en donde hay seis elementos. ","audio":"https://ucarecdn.com/0fdcc28d-cf82-41e6-92f1-a2398d11cbb2/","v-bind:autoplay":true,"class":""},"content":[],"id":"Instruccion","location":"1,0,0"}],"id":"LaterialInfo","location":"1,0"},{"name":"av-activity","odatype":"avanzadas","active":true,"minimize":false,"binds":{},"attr":{"class":""},"content":[{"name":"layout-grid","active":true,"minimize":false,"binds":{},"attr":{"columns":2,"columns-md":2,"gap":"2","class":" p-10"},"content":[{"name":"layout-img","active":true,"minimize":false,"binds":{},"attr":{"v-bind:img-variable":null,"img":"https://ucarecdn.com/b45566ca-a0b0-498f-82cb-9754530f911d/","class":" mx-auto my-auto w-44"},"content":[],"id":"048ed3a98","location":"1,1,0,0"},{"name":"layout-grid","active":true,"minimize":false,"binds":{},"attr":{"columns":1,"columns-md":2,"gap":"2","class":""},"content":[{"name":"module-select","active":true,"minimize":false,"binds":{},"attr":{"v-bind:allok":false,"v-bind:answer":false,"class":" w-fit h-fit",":inmediate":true},"content":[{"name":"layout-img","active":true,"minimize":false,"binds":{},"attr":{"v-bind:img-variable":null,"img":"https://ucarecdn.com/5273fc8b-5cef-40c3-a48f-30cb5b7a7e42/","class":""},"content":[],"id":"008b6b262","location":"1,1,0,1,0,0"}],"id":"075e7dd7e","location":"1,1,0,1,0"},{"name":"module-select","active":true,"minimize":false,"binds":{},"attr":{"v-bind:allok":false,"v-bind:answer":false,"class":" w-fit h-fit",":inmediate":true},"content":[{"name":"layout-img","active":true,"minimize":false,"binds":{},"attr":{"v-bind:img-variable":null,"img":"https://ucarecdn.com/49d08bdd-82ec-444f-a1f9-4fe9b1deaae3/","class":""},"content":[],"id":"008b6b262","location":"1,1,0,1,1,0"}],"id":"b93b3776","location":"1,1,0,1,1"},{"name":"module-select","active":true,"minimize":false,"binds":{},"attr":{"v-bind:allok":false,"v-bind:answer":false,"class":" w-fit h-fit",":inmediate":true},"content":[{"name":"layout-img","active":true,"minimize":false,"binds":{},"attr":{"v-bind:img-variable":null,"img":"https://ucarecdn.com/1a43a7cc-7456-4fd6-8d15-b286a722c8c6/","class":""},"content":[],"id":"008b6b262","location":"1,1,0,1,2,0"}],"id":"b9c1769a","location":"1,1,0,1,2"},{"name":"module-select","active":true,"minimize":false,"binds":{},"attr":{"v-bind:allok":false,"v-bind:answer":true,"class":" w-fit h-fit",":inmediate":true},"content":[{"name":"layout-img","active":true,"minimize":false,"binds":{},"attr":{"v-bind:img-variable":null,"img":"https://ucarecdn.com/ef8859b3-8bb5-4b4e-abc4-8c20cadd5f81/","class":""},"content":[],"id":"008b6b262","location":"1,1,0,1,3,0"}],"id":"9cb5a22b","location":"1,1,0,1,3"}],"id":"1fedc8bf4","location":"1,1,0,1"}],"id":"094671dd6","location":"1,1,0"}],"id":"Actividad","location":"1,1"}],"id":"Escena 1","location":"1"},{"name":"av-scene","odatype":"avanzadas","active":true,"minimize":false,"binds":{},"attr":{"class":"","v-bind:automatic-scene":true},"content":[{"name":"av-end","odatype":"avanzadas","active":true,"minimize":false,"binds":{},"attr":{},"content":[],"id":"FinalizarODA","location":"2,0"}],"id":"Finalizar","location":"2"}],"view":false,"version":"0.6","loaderVersion":"v1.2.6","loader":"https://cdn.jsdelivr.net/gh/bluemx/blueodasv2@v1.2.6/lib/loader.min.js","mediafiles":[{"name":"02.png","uuid":"5273fc8b-5cef-40c3-a48f-30cb5b7a7e42","cdn":"https://ucarecdn.com/5273fc8b-5cef-40c3-a48f-30cb5b7a7e42/","isImage":true,"mimeType":"image/png"},{"name":"01.png","uuid":"b45566ca-a0b0-498f-82cb-9754530f911d","cdn":"https://ucarecdn.com/b45566ca-a0b0-498f-82cb-9754530f911d/","isImage":true,"mimeType":"image/png"},{"name":"04.png","uuid":"1a43a7cc-7456-4fd6-8d15-b286a722c8c6","cdn":"https://ucarecdn.com/1a43a7cc-7456-4fd6-8d15-b286a722c8c6/","isImage":true,"mimeType":"image/png"},{"name":"03.png","uuid":"49d08bdd-82ec-444f-a1f9-4fe9b1deaae3","cdn":"https://ucarecdn.com/49d08bdd-82ec-444f-a1f9-4fe9b1deaae3/","isImage":true,"mimeType":"image/png"},{"name":"05.png","uuid":"ef8859b3-8bb5-4b4e-abc4-8c20cadd5f81","cdn":"https://ucarecdn.com/ef8859b3-8bb5-4b4e-abc4-8c20cadd5f81/","isImage":true,"mimeType":"image/png"},{"name":"MATEMATICAS2_DONDEHAY6.wav","uuid":"0fdcc28d-cf82-41e6-92f1-a2398d11cbb2","cdn":"https://ucarecdn.com/0fdcc28d-cf82-41e6-92f1-a2398d11cbb2/","isImage":false,"mimeType":"audio/wav"}]}