{"title":"Ricas hortalizas","subtitle":"","data":[{"name":"oda-instruccion","attr":{"class":""},"content":"Usa el primer campo para ingresar la cantidad de hortalizas que hay, en el segundo campo la cantidad de ellas que se necesitan cosechar y, finalmente, usa el tercer campo para responder: ¿cuántas hortalizas quedarán después de cosechar las que se necesitan?  ","id":"0e4397cd1","location":"0"},{"name":"layout-img","attr":{"img":"https://ucarecdn.com/4f44063c-25d6-4f1a-b765-4ac225ba31e2/","class":""},"content":[],"id":"1cb0024a0","location":"1"},{"name":"layout-grid","attr":{"columns":5,"columns-md":5,"gap":"2","class":" p-2 mx-auto my-5 text-center items-center w-3/4 bg-pastel2"},"content":[{"name":"module-input","attr":{"answer":"10","placeholder":"","class":""},"content":[],"id":"0966e7f37","location":"2,0"},{"name":"span","attr":{"class":""},"content":"menos","id":"12a5ae34e","location":"2,1"},{"name":"module-input","attr":{"answer":"5","placeholder":"","class":""},"content":[],"id":"39d0aae8","location":"2,2"},{"name":"span","attr":{"class":""},"content":"quedan","id":"510cb8dd","location":"2,3"},{"name":"module-input","attr":{"answer":"5","placeholder":"","class":""},"content":[],"id":"cb3ff9b9","location":"2,4"}],"id":"pregunta1","location":"2"},{"name":"layout-img","attr":{"img":"https://ucarecdn.com/f9b43a79-2af5-4064-a48d-93ab3c7aa5d3/","class":""},"content":[],"id":"8bdbfba5","location":"3"},{"name":"layout-grid","attr":{"columns":5,"columns-md":5,"gap":"2","class":" p-2 mx-auto my-5 text-center items-center w-3/4 bg-pastel4"},"content":[{"name":"module-input","attr":{"answer":"10","placeholder":"","class":""},"content":[],"id":"0966e7f37","location":"4,0"},{"name":"span","attr":{"class":""},"content":"menos","id":"12a5ae34e","location":"4,1"},{"name":"module-input","attr":{"answer":"3","placeholder":"","class":""},"content":[],"id":"39d0aae8","location":"4,2"},{"name":"span","attr":{"class":""},"content":"quedan","id":"510cb8dd","location":"4,3"},{"name":"module-input","attr":{"answer":"7","placeholder":"","class":""},"content":[],"id":"cb3ff9b9","location":"4,4"}],"id":"pregunta2","location":"4"},{"name":"layout-img","attr":{"img":"https://ucarecdn.com/f1c77464-d6fe-4679-bef7-f02b636707a8/","class":""},"content":[],"id":"789d8bfb","location":"5"},{"name":"layout-grid","attr":{"columns":5,"columns-md":5,"gap":"2","class":" p-2 mx-auto my-5 text-center items-center w-3/4 bg-pastel5"},"content":[{"name":"module-input","attr":{"answer":"10","placeholder":"","class":""},"content":[],"id":"0966e7f37","location":"6,0"},{"name":"span","attr":{"class":""},"content":"menos","id":"12a5ae34e","location":"6,1"},{"name":"module-input","attr":{"answer":"6","placeholder":"","class":""},"content":[],"id":"39d0aae8","location":"6,2"},{"name":"span","attr":{"class":""},"content":"quedan","id":"510cb8dd","location":"6,3"},{"name":"module-input","attr":{"answer":"4","placeholder":"","class":""},"content":[],"id":"cb3ff9b9","location":"6,4"}],"id":"pregunta3","location":"6"}],"view":false,"version":"0.12","loaderVersion":"v1.0.15","loader":"https://cdn.jsdelivr.net/gh/bluemx/blueodasv2@v1.0.15/basicas/assets/loader.min.js","mediafiles":[{"name":"02_1.png","uuid":"f9b43a79-2af5-4064-a48d-93ab3c7aa5d3","cdn":"https://ucarecdn.com/f9b43a79-2af5-4064-a48d-93ab3c7aa5d3/"},{"name":"01_1.png","uuid":"4f44063c-25d6-4f1a-b765-4ac225ba31e2","cdn":"https://ucarecdn.com/4f44063c-25d6-4f1a-b765-4ac225ba31e2/"},{"name":"03_1.png","uuid":"f1c77464-d6fe-4679-bef7-f02b636707a8","cdn":"https://ucarecdn.com/f1c77464-d6fe-4679-bef7-f02b636707a8/"}]}